fixed_timezone_field
