Metadata-Version: 1.0
Name: django-fixed-timezone-field
Version: 1.0.4
Summary: Ignore the activated timezone.
Home-page: https://github.com/matix-io/django-fixed-timezone-field
Author: Connor Bode
Author-email: connor@matix.io
License: MIT
Platform: UNKNOWN
